application/__init__.py
application/services/__init__.py
application/services/writer/WriterService.py
application/services/writer/__init__.py
application/services/writer/test_WriterService.py
domain/__init__.py
domain/entities/__init__.py
domain/entities/bookmark/Bookmark.py
domain/entities/bookmark/__init__.py
domain/entities/bookmark/test_Bookmark.py
domain/entities/folder/Folder.py
domain/entities/folder/__init__.py
domain/entities/folder/test_Folder.py
domain/entities/whitelist/Whitelist.py
domain/entities/whitelist/__init__.py
domain/entities/whitelist/test_Whitelist.py
domain/interfaces/__init__.py
domain/interfaces/JSONable/JSONable.py
domain/interfaces/JSONable/__init__.py
domain/repositories/__init__.py
domain/repositories/bookmark/IBookmarkRepo.py
domain/repositories/bookmark/__init__.py
domain/repositories/whitelist/IWhitelistRepo.py
domain/repositories/whitelist/__init__.py
infrastructure/__init__.py
infrastructure/persistance/__init__.py
infrastructure/persistance/adapters/__init__.py
infrastructure/persistance/adapters/bookmark/__init__.py
infrastructure/persistance/adapters/bookmark/brave/BraveBookmarkRepo.py
infrastructure/persistance/adapters/bookmark/brave/__init__.py
infrastructure/persistance/adapters/bookmark/brave/test_BraveBookmarkRepo.py
infrastructure/persistance/adapters/whitelist/__init__.py
infrastructure/persistance/adapters/whitelist/fs/FSWhitelistRepo.py
infrastructure/persistance/adapters/whitelist/fs/__init__.py
infrastructure/persistance/adapters/whitelist/fs/test_FSWhitelistRepo.py
presentation/__init__.py
presentation/cli/__init__.py
presentation/cli/__main__.py
bkmks-2.0.0.dist-info/LICENSE
bkmks-2.0.0.dist-info/METADATA
bkmks-2.0.0.dist-info/WHEEL
bkmks-2.0.0.dist-info/entry_points.txt
bkmks-2.0.0.dist-info/top_level.txt
bkmks-2.0.0.dist-info/RECORD
