Metadata-Version: 2.1
Name: bkmks
Version: 2.0.0
Summary: Extendable browser bookmark exporter CLI tool
Home-page: https://github.com/nico-i/bkmks
Author: Nico Ismaili
Author-email: nico@ismaili.de
Project-URL: Bug Reports, https://github.com/nico-i/bkmks/issues
Project-URL: Funding, https://www.paypal.com/paypalme/ismailinico
Project-URL: Source, https://github.com/nico-i/bkmks
Keywords: bookmark,browser,export
Requires-Python: >=3.12, <4
License-File: LICENSE
Requires-Dist: pathspec
Requires-Dist: questionary
Provides-Extra: dev
Requires-Dist: ruff; extra == "dev"
Requires-Dist: pyinstaller; extra == "dev"
Provides-Extra: test
Requires-Dist: pytest; extra == "test"
